{
  "project_info": {
    "project_id": "cfood-396c0",
    "project_number": "535133034868",
    "name": "cFood"
  },
  "client": [
    {
      "client_info": {
        "mobilesdk_app_id": "1:535133034868:android:ec2a3638813eedfd",
        "client_id": "android:com.project.cFood",
        "client_type": 1,
        "android_client_info": {
          "package_name": "com.project.cFood",
          "certificate_hash": []
        }
      },
      "oauth_client": [
        {
          "client_id": "535133034868-hp8vgdri6bc7ic96g9e7hkoob8abutnm.apps.googleusercontent.com",
          "client_type": 1,
          "android_info": {
            "package_name": "com.project.cFood",
            "certificate_hash": "D169A90D2BA2EE898ACA0C6E335732D5E38CB498"
          }
        },
        {
          "client_id": "535133034868-hp8vgdri6bc7ic96g9e7hkoob8abutnm.apps.googleusercontent.com",
          "client_type": 3
        }
      ],
      "api_key": [],
      "services": {
        "analytics_service": {
          "status": 1
        },
        "cloud_messaging_service": {
          "status": 1,
          "apns_config": []
        },
        "appinvite_service": {
          "status": 1,
          "other_platform_oauth_client": []
        },
        "google_signin_service": {
          "status": 2
        },
        "ads_service": {
          "status": 1
        }
      }
    }
  ],
  "client_info": [],
  "ARTIFACT_VERSION": "1"
}